{ "_id" : "eP3peunRsx9C42Rrq", "project" : "USACE Field Research Facility", "projectId" : "xWPTFT6HLPZhJHyqQ", "stationName" : "FRF - Atlantic Ocean", "stationNumber" : "N/A", "stationLoc" : "FRF nearshore", "owner" : "USACE-FRF", "description" : "Atlantic Ocean at the FRF", "status" : "Active", "lat" : 36.18184, "lon" : -75.7512, "waterDepth" : 8, "createdAt" : { "$date" : "2018-03-29T17:08:28.423-0400" }, "createdBy" : "d3tATrDSGfhPnckgH", "updatedAt" : { "$date" : "2018-03-29T17:18:45.375-0400" }, "updatedBy" : "admin@localuser.com" }
